HTMLTemplateRender/VERSION
HTMLTemplateRender/__init__.py
HTMLTemplateRender/renderer.py
HTMLTemplateRender/version.py
HTMLTemplateRender-1.0.1.dist-info/METADATA
HTMLTemplateRender-1.0.1.dist-info/WHEEL
HTMLTemplateRender-1.0.1.dist-info/top_level.txt
HTMLTemplateRender-1.0.1.dist-info/RECORD
