Metadata-Version: 2.1
Name: HTMLTemplateRender
Version: 1.0.1
Summary: Html template renderer
Home-page: https://github.com/QuackCoding/HTMLTemplateRender
Author: Aiden (Dev)
Author-email: 
License: UNKNOWN
Keywords: python,HTML,template,html template renderer,HTMLTemplateRender
Platform: UNKNOWN
Classifier: Development Status :: 5 - Production/Stable
Classifier: Intended Audience :: Developers
Classifier: Programming Language :: Python :: 3
Classifier: Operating System :: Unix
Classifier: Operating System :: MacOS :: MacOS X
Classifier: Operating System :: Microsoft :: Windows
